ladybug_radiance/__init__.py
ladybug_radiance/config.json
ladybug_radiance/config.py
ladybug_radiance/intersection.py
ladybug_radiance/skymatrix.py
ladybug_radiance/study/__init__.py
ladybug_radiance/study/directsun.py
ladybug_radiance/study/radiation.py
ladybug_radiance/visualize/__init__.py
ladybug_radiance/visualize/raddome.py
ladybug_radiance/visualize/radrose.py
ladybug_radiance/visualize/skydome.py
ladybug_radiance-0.2.10.dist-info/LICENSE
ladybug_radiance-0.2.10.dist-info/METADATA
ladybug_radiance-0.2.10.dist-info/WHEEL
ladybug_radiance-0.2.10.dist-info/top_level.txt
ladybug_radiance-0.2.10.dist-info/RECORD
