Metadata-Version: 2.1
Name: ladybug-radiance
Version: 0.2.10
Summary: Radiance extension for Ladybug, used for all radiation studies and graphics.
Home-page: https://github.com/ladybug-tools/ladybug-radiance
Author: Ladybug Tools
Author-email: info@ladybug.tools
License: AGPL-3.0
Classifier: Programming Language :: Python :: 2.7
Classifier: Programming Language :: Python :: 3.7
Classifier: Programming Language :: Python :: Implementation :: CPython
Classifier: License :: OSI Approved :: GNU Affero General Public License v3
Classifier: Operating System :: OS Independent
Provides-Extra: display
License-File: LICENSE
